vieutil/__init__.py
vieutil/send_email.py
vieutil/viecry.py
vieutil/vieldap.py
vieutil/vielog.py
vieutil-0.5.dist-info/LICENSE.txt
vieutil-0.5.dist-info/METADATA
vieutil-0.5.dist-info/WHEEL
vieutil-0.5.dist-info/top_level.txt
vieutil-0.5.dist-info/RECORD
