Metadata-Version: 2.1
Name: vieutil
Version: 0.5
Summary: Password encryption
Home-page: https://github.com/ftonioloviemar/vieutil
Download-URL: https://github.com/ftonioloviemar/vieutil/archive/refs/tags/V_0.3.tar.gz
Author: Fabio Toniolo Vieira Junior
Author-email: ftoniolo@viemar.com.br
License: MIT
Keywords: viemar,util,cryptography,logging,send_email
Classifier: Development Status :: 3 - Alpha
Classifier: Intended Audience :: Developers
Classifier: Topic :: Software Development :: Build Tools
Classifier: License :: OSI Approved :: MIT License
Classifier: Programming Language :: Python :: 3.0
Classifier: Programming Language :: Python :: 3.1
Classifier: Programming Language :: Python :: 3.2
Classifier: Programming Language :: Python :: 3.3
Classifier: Programming Language :: Python :: 3.4
Classifier: Programming Language :: Python :: 3.5
Classifier: Programming Language :: Python :: 3.6
Classifier: Programming Language :: Python :: 3.7
Classifier: Programming Language :: Python :: 3.8
Classifier: Programming Language :: Python :: 3.9
Classifier: Programming Language :: Python :: 3.10
Classifier: Programming Language :: Python :: 3.11
Classifier: Programming Language :: Python :: 3.12
License-File: LICENSE.txt
Requires-Dist: cryptography
Requires-Dist: tenacity
